ytxd/__init__.py
ytxd/__main__.py
ytxd/dependencies.py
ytxd/download.py
ytxd/main.py
ytxd/media_formats.py
ytxd/url.py
ytxd-0.0.1.dist-info/LICENSE
ytxd-0.0.1.dist-info/METADATA
ytxd-0.0.1.dist-info/WHEEL
ytxd-0.0.1.dist-info/entry_points.txt
ytxd-0.0.1.dist-info/top_level.txt
ytxd-0.0.1.dist-info/RECORD
