Metadata-Version: 2.1
Name: ytxd
Version: 0.0.1
Summary: A user-friendly cli tool for downloading video and audio from url. YTXD is wrapper around the yt-dlp.
Author-email: Mateusz Gancarek <mateusz.gancarek@outlook.com>
License: This is free and unencumbered software released into the public domain.
Project-URL: Homepage, https://github.com/imoneo/ytxd
Keywords: audio,cli,downloader,video,ffmpeg,youtube-dl,typer,uv,yt-dlp
Requires-Python: >=3.12
License-File: LICENSE
Requires-Dist: python-slugify >=8.0.4
Requires-Dist: typer >=0.12.5
Requires-Dist: yt-dlp >=2024.10.7
